{"GUID":"4b26035c-4743-4a72-b8fb-614cf900094e","CountryISOCode":"SE","RegionGUID":"8d855241-afa9-4df5-aea7-8a0d7d47a573","ID":"330","Name":"Johannesberg Golfklubb","DisplayName":"Johannesberg Golfklubb","ShortName":"JobGK","MapLat":"59.730296861879175","MapLng":"18.192050402392574","MapZoom":12,"ExternalID":"4b26035c-4743-4a72-b8fb-614cf900094e","Data":{"Note":"","WebPayment":"Nej","Courses":[{"Name":"18-Hålsbanan","Note":"18 håls Champions course samt en fullängds 9 håls pay & play bana. Båda designade av Donald Steel. Pool i klubbhuset.Information om våra golfpaket på Johannesbergs Slott och Golfhotellet se vår hemsida www.johannesberg.se","GeneralStartInfo":"","Loop":{"Name":"18-Hålsbanan","Note":"Park och skogsbana","GreenNote":"","GreenOpen":true,"LoopOpen":true,"TemporaryGreens":false,"Active":true,"HCPAltering":true,"Slopes":[{"CourseRating":74.2,"SlopeValue":135,"Gender":1,"TeeColor":"Vit"},{"CourseRating":77.9,"SlopeValue":137,"Gender":0,"TeeColor":"Gul"},{"CourseRating":71.9,"SlopeValue":130,"Gender":1,"TeeColor":"Gul"},{"CourseRating":74.8,"SlopeValue":131,"Gender":0,"TeeColor":"Blå"},{"CourseRating":69.4,"SlopeValue":125,"Gender":1,"TeeColor":"Blå"},{"CourseRating":73.4,"SlopeValue":128,"Gender":0,"TeeColor":"Röd"},{"CourseRating":68.3,"SlopeValue":123,"Gender":1,"TeeColor":"Röd"},{"CourseRating":67.3,"SlopeValue":115,"Gender":0,"TeeColor":"Orange"}],"Holes":[{"Number":1,"Name":"Hål 1","Note":"18-hålsbanan","HoleSponsor":"","GreenCenterLatitude":null,"GreenCenterLongitude":null,"GreenFrontLatitude":null,"GreenFrontLongitude":null,"GrenDepth":0.0,"Tees":[{"Color":"Orange","ColorCode":null,"Length":220,"Type":"Grästee","TeeLatitude":null,"TeeLongitude":null},{"Color":"Blå","ColorCode":null,"Length":262,"Type":"Grästee","TeeLatitude":null,"TeeLongitude":null},{"Color":"Röd","ColorCode":null,"Length":220,"Type":"Grästee","TeeLatitude":null,"TeeLongitude":null},{"Color":"Vit","ColorCode":null,"Length":273,"Type":"Grästee","TeeLatitude":null,"TeeLongitude":null},{"Color":"Gul","ColorCode":null,"Length":262,"Type":"Grästee","TeeLatitude":null,"TeeLongitude":null}],"Par":4,"Index":17},{"Number":2,"Name":"Hål 2","Note":"18-hålsbanan","HoleSponsor":"","GreenCenterLatitude":null,"GreenCenterLongitude":null,"GreenFrontLatitude":null,"GreenFrontLongitude":null,"GrenDepth":0.0,"Tees":[{"Color":"Orange","ColorCode":null,"Length":217,"Type":"Grästee","TeeLatitude":null,"TeeLongitude":null},{"Color":"Blå","ColorCode":null,"Length":323,"Type":"Grästee","TeeLatitude":null,"TeeLongitude":null},{"Color":"Röd","ColorCode":null,"Length":292,"Type":"Grästee","TeeLatitude":null,"TeeLongitude":null},{"Color":"Vit","ColorCode":null,"Length":344,"Type":"Grästee","TeeLatitude":null,"TeeLongitude":null},{"Color":"Gul","ColorCode":null,"Length":323,"Type":"Grästee","TeeLatitude":null,"TeeLongitude":null}],"Par":4,"Index":11},{"Number":3,"Name":"Hål 3","Note":"18-hålsbanan","HoleSponsor":"","GreenCenterLatitude":null,"GreenCenterLongitude":null,"GreenFrontLatitude":null,"GreenFrontLongitude":null,"GrenDepth":0.0,"Tees":[{"Color":"Orange","ColorCode":null,"Length":291,"Type":"Grästee","TeeLatitude":null,"TeeLongitude":null},{"Color":"Blå","ColorCode":null,"Length":391,"Type":"Grästee","TeeLatitude":null,"TeeLongitude":null},{"Color":"Röd","ColorCode":null,"Length":391,"Type":"Grästee","TeeLatitude":null,"TeeLongitude":null},{"Color":"Vit","ColorCode":null,"Length":492,"Type":"Grästee","TeeLatitude":null,"TeeLongitude":null},{"Color":"Gul","ColorCode":null,"Length":452,"Type":"Grästee","TeeLatitude":null,"TeeLongitude":null}],"Par":5,"Index":7},{"Number":4,"Name":"Hål 4","Note":"18-hålsbanan","HoleSponsor":"","GreenCenterLatitude":null,"GreenCenterLongitude":null,"GreenFrontLatitude":null,"GreenFrontLongitude":null,"GrenDepth":0.0,"Tees":[{"Color":"Orange","ColorCode":null,"Length":220,"Type":"Grästee","TeeLatitude":null,"TeeLongitude":null},{"Color":"Blå","ColorCode":null,"Length":373,"Type":"Grästee","TeeLatitude":null,"TeeLongitude":null},{"Color":"Röd","ColorCode":null,"Length":325,"Type":"Grästee","TeeLatitude":null,"TeeLongitude":null},{"Color":"Vit","ColorCode":null,"Length":431,"Type":"Grästee","TeeLatitude":null,"TeeLongitude":null},{"Color":"Gul","ColorCode":null,"Length":399,"Type":"Grästee","TeeLatitude":null,"TeeLongitude":null}],"Par":4,"Index":1},{"Number":5,"Name":"Hål 5","Note":"18-hålsbanan","HoleSponsor":"","GreenCenterLatitude":null,"GreenCenterLongitude":null,"GreenFrontLatitude":null,"GreenFrontLongitude":null,"GrenDepth":0.0,"Tees":[{"Color":"Orange","ColorCode":null,"Length":246,"Type":"Grästee","TeeLatitude":null,"TeeLongitude":null},{"Color":"Blå","ColorCode":null,"Length":326,"Type":"Grästee","TeeLatitude":null,"TeeLongitude":null},{"Color":"Röd","ColorCode":null,"Length":326,"Type":"Grästee","TeeLatitude":null,"TeeLongitude":null},{"Color":"Vit","ColorCode":null,"Length":393,"Type":"Grästee","TeeLatitude":null,"TeeLongitude":null},{"Color":"Gul","ColorCode":null,"Length":362,"Type":"Grästee","TeeLatitude":null,"TeeLongitude":null}],"Par":4,"Index":3},{"Number":6,"Name":"Hål 6","Note":"18-hålsbanan","HoleSponsor":"","GreenCenterLatitude":null,"GreenCenterLongitude":null,"GreenFrontLatitude":null,"GreenFrontLongitude":null,"GrenDepth":0.0,"Tees":[{"Color":"Orange","ColorCode":null,"Length":73,"Type":"Grästee","TeeLatitude":null,"TeeLongitude":null},{"Color":"Blå","ColorCode":null,"Length":143,"Type":"Grästee","TeeLatitude":null,"TeeLongitude":null},{"Color":"Röd","ColorCode":null,"Length":143,"Type":"Grästee","TeeLatitude":null,"TeeLongitude":null},{"Color":"Vit","ColorCode":null,"Length":190,"Type":"Grästee","TeeLatitude":null,"TeeLongitude":null},{"Color":"Gul","ColorCode":null,"Length":169,"Type":"Grästee","TeeLatitude":null,"TeeLongitude":null}],"Par":3,"Index":9},{"Number":7,"Name":"Hål 7","Note":"18-hålsbanan","HoleSponsor":"","GreenCenterLatitude":null,"GreenCenterLongitude":null,"GreenFrontLatitude":null,"GreenFrontLongitude":null,"GrenDepth":0.0,"Tees":[{"Color":"Orange","ColorCode":null,"Length":326,"Type":"Grästee","TeeLatitude":null,"TeeLongitude":null},{"Color":"Blå","ColorCode":null,"Length":400,"Type":"Grästee","TeeLatitude":null,"TeeLongitude":null},{"Color":"Röd","ColorCode":null,"Length":400,"Type":"Grästee","TeeLatitude":null,"TeeLongitude":null},{"Color":"Vit","ColorCode":null,"Length":469,"Type":"Grästee","TeeLatitude":null,"TeeLongitude":null},{"Color":"Gul","ColorCode":null,"Length":436,"Type":"Grästee","TeeLatitude":null,"TeeLongitude":null}],"Par":5,"Index":5},{"Number":8,"Name":"Hål 8","Note":"18-hålsbanan","HoleSponsor":"","GreenCenterLatitude":null,"GreenCenterLongitude":null,"GreenFrontLatitude":null,"GreenFrontLongitude":null,"GrenDepth":0.0,"Tees":[{"Color":"Orange","ColorCode":null,"Length":224,"Type":"Grästee","TeeLatitude":null,"TeeLongitude":null},{"Color":"Blå","ColorCode":null,"Length":299,"Type":"Grästee","TeeLatitude":null,"TeeLongitude":null},{"Color":"Röd","ColorCode":null,"Length":299,"Type":"Grästee","TeeLatitude":null,"TeeLongitude":null},{"Color":"Vit","ColorCode":null,"Length":355,"Type":"Grästee","TeeLatitude":null,"TeeLongitude":null},{"Color":"Gul","ColorCode":null,"Length":321,"Type":"Grästee","TeeLatitude":null,"TeeLongitude":null}],"Par":4,"Index":13},{"Number":9,"Name":"Hål 9","Note":"18-hålsbanan","HoleSponsor":"","GreenCenterLatitude":null,"GreenCenterLongitude":null,"GreenFrontLatitude":null,"GreenFrontLongitude":null,"GrenDepth":0.0,"Tees":[{"Color":"Orange","ColorCode":null,"Length":82,"Type":"Grästee","TeeLatitude":null,"TeeLongitude":null},{"Color":"Blå","ColorCode":null,"Length":122,"Type":"Grästee","TeeLatitude":null,"TeeLongitude":null},{"Color":"Röd","ColorCode":null,"Length":122,"Type":"Grästee","TeeLatitude":null,"TeeLongitude":null},{"Color":"Vit","ColorCode":null,"Length":173,"Type":"Grästee","TeeLatitude":null,"TeeLongitude":null},{"Color":"Gul","ColorCode":null,"Length":161,"Type":"Grästee","TeeLatitude":null,"TeeLongitude":null}],"Par":3,"Index":15},{"Number":10,"Name":"Hål 10","Note":"18-hålsbanan","HoleSponsor":"","GreenCenterLatitude":null,"GreenCenterLongitude":null,"GreenFrontLatitude":null,"GreenFrontLongitude":null,"GrenDepth":0.0,"Tees":[{"Color":"Orange","ColorCode":null,"Length":189,"Type":"Grästee","TeeLatitude":null,"TeeLongitude":null},{"Color":"Blå","ColorCode":null,"Length":299,"Type":"Grästee","TeeLatitude":null,"TeeLongitude":null},{"Color":"Röd","ColorCode":null,"Length":299,"Type":"Grästee","TeeLatitude":null,"TeeLongitude":null},{"Color":"Vit","ColorCode":null,"Length":411,"Type":"Grästee","TeeLatitude":null,"TeeLongitude":null},{"Color":"Gul","ColorCode":null,"Length":360,"Type":"Grästee","TeeLatitude":null,"TeeLongitude":null}],"Par":4,"Index":8},{"Number":11,"Name":"Hål 11","Note":"18-hålsbanan","HoleSponsor":"","GreenCenterLatitude":null,"GreenCenterLongitude":null,"GreenFrontLatitude":null,"GreenFrontLongitude":null,"GrenDepth":0.0,"Tees":[{"Color":"Orange","ColorCode":null,"Length":288,"Type":"Grästee","TeeLatitude":null,"TeeLongitude":null},{"Color":"Blå","ColorCode":null,"Length":312,"Type":"Grästee","TeeLatitude":null,"TeeLongitude":null},{"Color":"Röd","ColorCode":null,"Length":288,"Type":"Grästee","TeeLatitude":null,"TeeLongitude":null},{"Color":"Vit","ColorCode":null,"Length":344,"Type":"Grästee","TeeLatitude":null,"TeeLongitude":null},{"Color":"Gul","ColorCode":null,"Length":312,"Type":"Grästee","TeeLatitude":null,"TeeLongitude":null}],"Par":4,"Index":16},{"Number":12,"Name":"Hål 12","Note":"18-hålsbanan","HoleSponsor":"","GreenCenterLatitude":null,"GreenCenterLongitude":null,"GreenFrontLatitude":null,"GreenFrontLongitude":null,"GrenDepth":0.0,"Tees":[{"Color":"Orange","ColorCode":null,"Length":312,"Type":"Grästee","TeeLatitude":null,"TeeLongitude":null},{"Color":"Blå","ColorCode":null,"Length":312,"Type":"Grästee","TeeLatitude":null,"TeeLongitude":null},{"Color":"Röd","ColorCode":null,"Length":312,"Type":"Grästee","TeeLatitude":null,"TeeLongitude":null},{"Color":"Vit","ColorCode":null,"Length":374,"Type":"Grästee","TeeLatitude":null,"TeeLongitude":null},{"Color":"Gul","ColorCode":null,"Length":335,"Type":"Grästee","TeeLatitude":null,"TeeLongitude":null}],"Par":4,"Index":6},{"Number":13,"Name":"Hål 13","Note":"18-hålsbanan","HoleSponsor":"","GreenCenterLatitude":null,"GreenCenterLongitude":null,"GreenFrontLatitude":null,"GreenFrontLongitude":null,"GrenDepth":0.0,"Tees":[{"Color":"Orange","ColorCode":null,"Length":103,"Type":"Grästee","TeeLatitude":null,"TeeLongitude":null},{"Color":"Blå","ColorCode":null,"Length":103,"Type":"Grästee","TeeLatitude":null,"TeeLongitude":null},{"Color":"Röd","ColorCode":null,"Length":103,"Type":"Grästee","TeeLatitude":null,"TeeLongitude":null},{"Color":"Vit","ColorCode":null,"Length":154,"Type":"Grästee","TeeLatitude":null,"TeeLongitude":null},{"Color":"Gul","ColorCode":null,"Length":154,"Type":"Grästee","TeeLatitude":null,"TeeLongitude":null}],"Par":3,"Index":18},{"Number":14,"Name":"Hål 14","Note":"18-hålsbanan","HoleSponsor":"","GreenCenterLatitude":null,"GreenCenterLongitude":null,"GreenFrontLatitude":null,"GreenFrontLongitude":null,"GrenDepth":0.0,"Tees":[{"Color":"Orange","ColorCode":null,"Length":196,"Type":"Grästee","TeeLatitude":null,"TeeLongitude":null},{"Color":"Blå","ColorCode":null,"Length":316,"Type":"Grästee","TeeLatitude":null,"TeeLongitude":null},{"Color":"Röd","ColorCode":null,"Length":257,"Type":"Grästee","TeeLatitude":null,"TeeLongitude":null},{"Color":"Vit","ColorCode":null,"Length":355,"Type":"Grästee","TeeLatitude":null,"TeeLongitude":null},{"Color":"Gul","ColorCode":null,"Length":316,"Type":"Grästee","TeeLatitude":null,"TeeLongitude":null}],"Par":4,"Index":12},{"Number":15,"Name":"Hål 15","Note":"18-hålsbanan","HoleSponsor":"","GreenCenterLatitude":null,"GreenCenterLongitude":null,"GreenFrontLatitude":null,"GreenFrontLongitude":null,"GrenDepth":0.0,"Tees":[{"Color":"Orange","ColorCode":null,"Length":273,"Type":"Grästee","TeeLatitude":null,"TeeLongitude":null},{"Color":"Blå","ColorCode":null,"Length":324,"Type":"Grästee","TeeLatitude":null,"TeeLongitude":null},{"Color":"Röd","ColorCode":null,"Length":273,"Type":"Grästee","TeeLatitude":null,"TeeLongitude":null},{"Color":"Vit","ColorCode":null,"Length":381,"Type":"Grästee","TeeLatitude":null,"TeeLongitude":null},{"Color":"Gul","ColorCode":null,"Length":350,"Type":"Grästee","TeeLatitude":null,"TeeLongitude":null}],"Par":4,"Index":2},{"Number":16,"Name":"Hål 16","Note":"18-hålsbanan","HoleSponsor":"","GreenCenterLatitude":null,"GreenCenterLongitude":null,"GreenFrontLatitude":null,"GreenFrontLongitude":null,"GrenDepth":0.0,"Tees":[{"Color":"Orange","ColorCode":null,"Length":363,"Type":"Grästee","TeeLatitude":null,"TeeLongitude":null},{"Color":"Blå","ColorCode":null,"Length":396,"Type":"Grästee","TeeLatitude":null,"TeeLongitude":null},{"Color":"Röd","ColorCode":null,"Length":363,"Type":"Grästee","TeeLatitude":null,"TeeLongitude":null},{"Color":"Vit","ColorCode":null,"Length":452,"Type":"Grästee","TeeLatitude":null,"TeeLongitude":null},{"Color":"Gul","ColorCode":null,"Length":441,"Type":"Grästee","TeeLatitude":null,"TeeLongitude":null}],"Par":5,"Index":10},{"Number":17,"Name":"Hål 17","Note":"18-hålsbanan","HoleSponsor":"","GreenCenterLatitude":null,"GreenCenterLongitude":null,"GreenFrontLatitude":null,"GreenFrontLongitude":null,"GrenDepth":0.0,"Tees":[{"Color":"Orange","ColorCode":null,"Length":102,"Type":"Grästee","TeeLatitude":null,"TeeLongitude":null},{"Color":"Blå","ColorCode":null,"Length":131,"Type":"Grästee","TeeLatitude":null,"TeeLongitude":null},{"Color":"Röd","ColorCode":null,"Length":102,"Type":"Grästee","TeeLatitude":null,"TeeLongitude":null},{"Color":"Vit","ColorCode":null,"Length":168,"Type":"Grästee","TeeLatitude":null,"TeeLongitude":null},{"Color":"Gul","ColorCode":null,"Length":131,"Type":"Grästee","TeeLatitude":null,"TeeLongitude":null}],"Par":3,"Index":14},{"Number":18,"Name":"Hål 18","Note":"18-hålsbanan","HoleSponsor":"","GreenCenterLatitude":null,"GreenCenterLongitude":null,"GreenFrontLatitude":null,"GreenFrontLongitude":null,"GrenDepth":0.0,"Tees":[{"Color":"Orange","ColorCode":null,"Length":360,"Type":"Grästee","TeeLatitude":null,"TeeLongitude":null},{"Color":"Blå","ColorCode":null,"Length":447,"Type":"Grästee","TeeLatitude":null,"TeeLongitude":null},{"Color":"Röd","ColorCode":null,"Length":447,"Type":"Grästee","TeeLatitude":null,"TeeLongitude":null},{"Color":"Vit","ColorCode":null,"Length":475,"Type":"Grästee","TeeLatitude":null,"TeeLongitude":null},{"Color":"Gul","ColorCode":null,"Length":475,"Type":"Grästee","TeeLatitude":null,"TeeLongitude":null}],"Par":5,"Index":4}],"ValidFrom":"20180101T000000","ValidTo":"20201101T000000","GPSInfoOK":false},"BookingInformation":"Våra öppettider är 8-17. Shop/reception finns på nedre plan och restaurangen på övre. Banans kiosk/WC återfinns efter hål 6, 13 och 15, där går det att betala kontant eller swish. Rangen tar betalkort. Vatten för påfyllnad finns på klubbhusets framsida.","NumberOfHoles":18,"Par":72,"Architect":"Donald Steel","PlayableFromYear":"1992"}],"Phones":[{"Number":"+46851450000","PhoneType":"Primary"},{"Number":"+46851450000","PhoneType":"Bokning"},{"Number":"+46851450000","PhoneType":"Kansli"}],"Addresses":[{"Addr":"Gottröra","AddrInfo1":"","AddrInfo2":null,"PostalCode":"76295","PostalAddress":"RIMBO","Region":null,"Country":null,"Type":null}],"ClubAttributes":[{"Key":"CLUB_RESIDENT","Value":"1"},{"Key":"CLUB_CAFE","Value":"1"},{"Key":"CLUB_DRIVINGRANGE","Value":"1"},{"Key":"CLUB_SHOWER","Value":"1"},{"Key":"CLUB_TRAILERPARK_ELECTRIC_SOCKETS","Value":"1"},{"Key":"CLUB_BUGGY_HIRE","Value":"1"},{"Key":"GOLF_PACKAGES","Value":"1"},{"Key":"PROSHOP_EMAIL","Value":"info@johannesberg.se"},{"Key":"PROSHOP_CONTACT","Value":""},{"Key":"PROSHOP_NAME","Value":"Johannesberg Golfshop"},{"Key":"PROSHOP_PHONE","Value":"+46851450000"},{"Key":"CLUB_GPS_CLUBHOUSE_LATITUD","Value":"59.730296861879175"},{"Key":"CLUB_GPS_CLUBHOUSE_LONGITUD","Value":"18.192050402392574"},{"Key":"CLUB_GREENFEE_WEEKEND_JUNIOR","Value":"250"},{"Key":"CLUB_GREENFEE_WEEKEND_SENIOR","Value":"500"},{"Key":"CLUB_GREENFEE_TEXT","Value":""},{"Key":"CLUB_GREENFEE_WEEKDAY_JUNIOR","Value":"200"},{"Key":"CLUB_GREENFEE_WEEKDAY_SENIOR","Value":"400"},{"Key":"CLUB_GREENCARDCLUB","Value":"1"},{"Key":"CLUB_HCPFRIENDLY","Value":"1"},{"Key":"CLUB_HOMEPAGE","Value":"www.johannesberg.se"},{"Key":"CLUB_DOGS_PROHIBITION","Value":"0"},{"Key":"CLUB_SHORTNAME","Value":"JobGK"},{"Key":"CLUB_CLUB_HIRE","Value":"1"},{"Key":"CLUB_SHORTTRACK","Value":"0"},{"Key":"CLUB_MOREGOLFKLUBB","Value":"0"},{"Key":"CLUB_LOCKERROOM","Value":"1"},{"Key":"CLUB_PAY_AND_PLAY","Value":"1"},{"Key":"CLUB_RESTAURANT","Value":"1"},{"Key":"CLUB_RESTRICTIONS","Value":"18-hålsbanan kan bokas på webben både av gäster och medlemmar. \nFullängds 9-hålsbanan kan spelas Pay&Play, bollränna.  "},{"Key":"CLUB_SGF_NUMBER","Value":"330"},{"Key":"CLUB_SHOP","Value":"1"},{"Key":"CLUB_SPIKES","Value":"1"},{"Key":"CLUB_CABIN_HIRE","Value":"0"},{"Key":"CLUB_TRAILERPARK","Value":"1"},{"Key":"CLUB_TROLLEY_HIRE","Value":"1"},{"Key":"CLUB_PRACTICEGREEN","Value":"1"},{"Key":"CLUB_PRACTICEAREA","Value":"1"}],"ContactAvailabilities":[{"Name":null,"DateFrom":"2020-04-18","DateTo":"2020-09-30","DayFrom":"Söndag","DayTo":"Söndag","TimeFrom":"08:00","TimeTo":"16:30","BreakFrom":"","BreakTo":""}],"Contacts":[{"Type":"Ordförande","FirstName":"Niklas","LastName":"Boström","EmailAddress":"","FullName":"Niklas Boström"},{"Type":"Klubbchef/VD/Intendent","FirstName":"Helen","LastName":"Schönbäck","EmailAddress":null,"FullName":"Helen Schönbäck"}],"OtherClubs":null,"Emails":[{"EmailAddress":"info@johannesberg.se"}],"Tournaments":null,"Booking":null},"WeatherData":null}