{"GUID":"706ecbff-f432-4dbb-bdb3-52cdf036ecc7","CountryISOCode":"SE","RegionGUID":"6a24ca2d-997d-4ee4-bd61-ce27ed2c0866","ID":"372","Name":"Lanna Golfklubb","DisplayName":"Lanna Golfklubb","ShortName":"LanGK","MapLat":"57.2111870","MapLng":"13.7745744","MapZoom":12,"ExternalID":"706ecbff-f432-4dbb-bdb3-52cdf036ecc7","Data":{"Note":"Golf för alla","WebPayment":"Ja","Courses":[{"Name":"Ängavattnet","Note":"Lanna Golfklubb erbjuder en trevlig och omväxlande 9-håls golfbana, \"Ängavattnet\", med 9 alternativa tees, vilket gör att den upplevs som en 18-hålsbana.","GeneralStartInfo":"","Loop":{"Name":"Ängavattnet 9 hål 18 tees","Note":"Lätt kuperad, utmanande skogsbana.\nLätt ondulerade, små till medelstora greener.\nMed alternativa tee där det är konstgrästee.\nGrässort: Rödven och rödsvingel.","GreenNote":"","GreenOpen":true,"LoopOpen":true,"TemporaryGreens":false,"Active":true,"HCPAltering":true,"Slopes":[{"CourseRating":74.4,"SlopeValue":131,"Gender":0,"TeeColor":"Gul"},{"CourseRating":68.3,"SlopeValue":126,"Gender":1,"TeeColor":"Gul"},{"CourseRating":69.6,"SlopeValue":120,"Gender":0,"TeeColor":"Röd"},{"CourseRating":64.7,"SlopeValue":118,"Gender":1,"TeeColor":"Röd"}],"Holes":[{"Number":1,"Name":"01","Note":"Konstgräs tee","HoleSponsor":"","GreenCenterLatitude":null,"GreenCenterLongitude":null,"GreenFrontLatitude":null,"GreenFrontLongitude":null,"GrenDepth":0.0,"Tees":[{"Color":"Röd","ColorCode":null,"Length":109,"Type":"Matta","TeeLatitude":null,"TeeLongitude":null},{"Color":"Gul","ColorCode":null,"Length":131,"Type":"Matta","TeeLatitude":null,"TeeLongitude":null}],"Par":3,"Index":15},{"Number":2,"Name":"02","Note":"Gräs tee","HoleSponsor":"","GreenCenterLatitude":null,"GreenCenterLongitude":null,"GreenFrontLatitude":null,"GreenFrontLongitude":null,"GrenDepth":0.0,"Tees":[{"Color":"Röd","ColorCode":null,"Length":241,"Type":"Grästee","TeeLatitude":null,"TeeLongitude":null},{"Color":"Gul","ColorCode":null,"Length":281,"Type":"Grästee","TeeLatitude":null,"TeeLongitude":null}],"Par":4,"Index":7},{"Number":3,"Name":"03","Note":"Gräs tee","HoleSponsor":"","GreenCenterLatitude":null,"GreenCenterLongitude":null,"GreenFrontLatitude":null,"GreenFrontLongitude":null,"GrenDepth":0.0,"Tees":[{"Color":"Röd","ColorCode":null,"Length":108,"Type":"Grästee","TeeLatitude":null,"TeeLongitude":null},{"Color":"Gul","ColorCode":null,"Length":140,"Type":"Grästee","TeeLatitude":null,"TeeLongitude":null}],"Par":3,"Index":5},{"Number":4,"Name":"04","Note":"Gul - gräs tee, Röd - konstgräs tee","HoleSponsor":"","GreenCenterLatitude":null,"GreenCenterLongitude":null,"GreenFrontLatitude":null,"GreenFrontLongitude":null,"GrenDepth":0.0,"Tees":[{"Color":"Röd","ColorCode":null,"Length":245,"Type":"Matta","TeeLatitude":null,"TeeLongitude":null},{"Color":"Gul","ColorCode":null,"Length":301,"Type":"Grästee","TeeLatitude":null,"TeeLongitude":null}],"Par":4,"Index":11},{"Number":5,"Name":"05","Note":"Gräs tee","HoleSponsor":"","GreenCenterLatitude":null,"GreenCenterLongitude":null,"GreenFrontLatitude":null,"GreenFrontLongitude":null,"GrenDepth":0.0,"Tees":[{"Color":"Röd","ColorCode":null,"Length":373,"Type":"Grästee","TeeLatitude":null,"TeeLongitude":null},{"Color":"Gul","ColorCode":null,"Length":452,"Type":"Grästee","TeeLatitude":null,"TeeLongitude":null}],"Par":5,"Index":3},{"Number":6,"Name":"06","Note":"Konstgräs tee","HoleSponsor":"","GreenCenterLatitude":null,"GreenCenterLongitude":null,"GreenFrontLatitude":null,"GreenFrontLongitude":null,"GrenDepth":0.0,"Tees":[{"Color":"Röd","ColorCode":null,"Length":237,"Type":"Matta","TeeLatitude":null,"TeeLongitude":null},{"Color":"Gul","ColorCode":null,"Length":291,"Type":"Matta","TeeLatitude":null,"TeeLongitude":null}],"Par":4,"Index":13},{"Number":7,"Name":"07","Note":"Gul - konstgräs tee, Röd - gräs tee","HoleSponsor":"","GreenCenterLatitude":null,"GreenCenterLongitude":null,"GreenFrontLatitude":null,"GreenFrontLongitude":null,"GrenDepth":0.0,"Tees":[{"Color":"Röd","ColorCode":null,"Length":141,"Type":"Grästee","TeeLatitude":null,"TeeLongitude":null},{"Color":"Gul","ColorCode":null,"Length":170,"Type":"Matta","TeeLatitude":null,"TeeLongitude":null}],"Par":3,"Index":17},{"Number":8,"Name":"08","Note":"Gräs tee","HoleSponsor":"","GreenCenterLatitude":null,"GreenCenterLongitude":null,"GreenFrontLatitude":null,"GreenFrontLongitude":null,"GrenDepth":0.0,"Tees":[{"Color":"Röd","ColorCode":null,"Length":412,"Type":"Grästee","TeeLatitude":null,"TeeLongitude":null},{"Color":"Gul","ColorCode":null,"Length":474,"Type":"Grästee","TeeLatitude":null,"TeeLongitude":null}],"Par":5,"Index":1},{"Number":9,"Name":"09","Note":"Konstgräs tee","HoleSponsor":"","GreenCenterLatitude":null,"GreenCenterLongitude":null,"GreenFrontLatitude":null,"GreenFrontLongitude":null,"GrenDepth":0.0,"Tees":[{"Color":"Röd","ColorCode":null,"Length":288,"Type":"Matta","TeeLatitude":null,"TeeLongitude":null},{"Color":"Gul","ColorCode":null,"Length":336,"Type":"Matta","TeeLatitude":null,"TeeLongitude":null}],"Par":4,"Index":9},{"Number":10,"Name":"10","Note":"Gräs tee","HoleSponsor":"","GreenCenterLatitude":null,"GreenCenterLongitude":null,"GreenFrontLatitude":null,"GreenFrontLongitude":null,"GrenDepth":0.0,"Tees":[{"Color":"Röd","ColorCode":null,"Length":137,"Type":"Grästee","TeeLatitude":null,"TeeLongitude":null},{"Color":"Gul","ColorCode":null,"Length":170,"Type":"Grästee","TeeLatitude":null,"TeeLongitude":null}],"Par":3,"Index":4},{"Number":11,"Name":"11","Note":"Konstgräs tee","HoleSponsor":"","GreenCenterLatitude":null,"GreenCenterLongitude":null,"GreenFrontLatitude":null,"GreenFrontLongitude":null,"GrenDepth":0.0,"Tees":[{"Color":"Röd","ColorCode":null,"Length":189,"Type":"Matta","TeeLatitude":null,"TeeLongitude":null},{"Color":"Gul","ColorCode":null,"Length":227,"Type":"Matta","TeeLatitude":null,"TeeLongitude":null}],"Par":4,"Index":12},{"Number":12,"Name":"12","Note":"Konstgräs tee","HoleSponsor":"","GreenCenterLatitude":null,"GreenCenterLongitude":null,"GreenFrontLatitude":null,"GreenFrontLongitude":null,"GrenDepth":0.0,"Tees":[{"Color":"Röd","ColorCode":null,"Length":98,"Type":"Matta","TeeLatitude":null,"TeeLongitude":null},{"Color":"Gul","ColorCode":null,"Length":102,"Type":"Matta","TeeLatitude":null,"TeeLongitude":null}],"Par":3,"Index":14},{"Number":13,"Name":"13","Note":"Gul - konstgräs tee, Röd - gräs tee","HoleSponsor":"","GreenCenterLatitude":null,"GreenCenterLongitude":null,"GreenFrontLatitude":null,"GreenFrontLongitude":null,"GrenDepth":0.0,"Tees":[{"Color":"Röd","ColorCode":null,"Length":230,"Type":"Grästee","TeeLatitude":null,"TeeLongitude":null},{"Color":"Gul","ColorCode":null,"Length":291,"Type":"Matta","TeeLatitude":null,"TeeLongitude":null}],"Par":4,"Index":10},{"Number":14,"Name":"14","Note":"Konstgräs tee","HoleSponsor":"","GreenCenterLatitude":null,"GreenCenterLongitude":null,"GreenFrontLatitude":null,"GreenFrontLongitude":null,"GrenDepth":0.0,"Tees":[{"Color":"Röd","ColorCode":null,"Length":349,"Type":"Matta","TeeLatitude":null,"TeeLongitude":null},{"Color":"Gul","ColorCode":null,"Length":420,"Type":"Matta","TeeLatitude":null,"TeeLongitude":null}],"Par":5,"Index":2},{"Number":15,"Name":"15","Note":"Gräs tee","HoleSponsor":"","GreenCenterLatitude":null,"GreenCenterLongitude":null,"GreenFrontLatitude":null,"GreenFrontLongitude":null,"GrenDepth":0.0,"Tees":[{"Color":"Röd","ColorCode":null,"Length":232,"Type":"Grästee","TeeLatitude":null,"TeeLongitude":null},{"Color":"Gul","ColorCode":null,"Length":266,"Type":"Grästee","TeeLatitude":null,"TeeLongitude":null}],"Par":4,"Index":18},{"Number":16,"Name":"16","Note":"Gräs tee","HoleSponsor":"","GreenCenterLatitude":null,"GreenCenterLongitude":null,"GreenFrontLatitude":null,"GreenFrontLongitude":null,"GrenDepth":0.0,"Tees":[{"Color":"Röd","ColorCode":null,"Length":120,"Type":"Grästee","TeeLatitude":null,"TeeLongitude":null},{"Color":"Gul","ColorCode":null,"Length":141,"Type":"Grästee","TeeLatitude":null,"TeeLongitude":null}],"Par":3,"Index":16},{"Number":17,"Name":"17","Note":"Konstgräs tee","HoleSponsor":"","GreenCenterLatitude":null,"GreenCenterLongitude":null,"GreenFrontLatitude":null,"GreenFrontLongitude":null,"GrenDepth":0.0,"Tees":[{"Color":"Röd","ColorCode":null,"Length":400,"Type":"Matta","TeeLatitude":null,"TeeLongitude":null},{"Color":"Gul","ColorCode":null,"Length":465,"Type":"Matta","TeeLatitude":null,"TeeLongitude":null}],"Par":5,"Index":8},{"Number":18,"Name":"18","Note":"Gräs tee","HoleSponsor":"","GreenCenterLatitude":null,"GreenCenterLongitude":null,"GreenFrontLatitude":null,"GreenFrontLongitude":null,"GrenDepth":0.0,"Tees":[{"Color":"Röd","ColorCode":null,"Length":314,"Type":"Grästee","TeeLatitude":null,"TeeLongitude":null},{"Color":"Gul","ColorCode":null,"Length":366,"Type":"Grästee","TeeLatitude":null,"TeeLongitude":null}],"Par":4,"Index":6}],"ValidFrom":"20200410T000000","ValidTo":"20200915T000000","GPSInfoOK":false},"BookingInformation":"Vid spel över 18 hål bör två rundor bokas. 9 hål brukar spelas på ca 2 timmar.OBS! Vid bokning av dubbla tider ska endast en avgift på 300 kr erläggas.","NumberOfHoles":18,"Par":70,"Architect":"","PlayableFromYear":"2013"}],"Phones":[{"Number":"+4637083338","PhoneType":"Primary"},{"Number":"+4637083338","PhoneType":"Kansli"},{"Number":"+4637083337","PhoneType":"Fax"}],"Addresses":[{"Addr":"Horshult Lanna","AddrInfo1":"","AddrInfo2":null,"PostalCode":"33010","PostalAddress":"BREDARYD","Region":null,"Country":null,"Type":null}],"ClubAttributes":[{"Key":"CLUB_RESIDENT","Value":"0"},{"Key":"CLUB_CAFE","Value":"1"},{"Key":"CLUB_DRIVINGRANGE","Value":"1"},{"Key":"CLUB_SHOWER","Value":"1"},{"Key":"CLUB_TRAILERPARK_ELECTRIC_SOCKETS","Value":"1"},{"Key":"CLUB_BUGGY_HIRE","Value":"1"},{"Key":"GOLFGUIDE_EXTENDEDINFO","Value":"Ängs- och hagmarkskaraktär\nHela anläggningen ligger i en fantastiskt vacker natur.\nBanorna är en utmaning.\nÄngavattnet - fullängdsbana, 9 hål med 18 tee.\nTrantorpsbanan - korthålsbana, 9 hål. Golf och Footgolf - Pay&play."},{"Key":"GOLF_PACKAGES","Value":"0"},{"Key":"RESTAURANT_EXTENDED_INFO","Value":"Servering av kaffe, the, choklad, läsk, frallor, bullar, kakor och choklad.\nVi serverar även våfflor med sylt och glass/grädde vissa dagar under kansliets öppettider.\nSjälvservering!"},{"Key":"RESTAURANT_OPENING_HOURS","Value":"Öppet 07:00-21:00 alla dagar"},{"Key":"GOLFGUIDE_ROUTE_DESCR","Value":"Rv 27, Bredaryd. Kör Lv 152 mot Skillingaryd ca 4 km, skylt golfbana."},{"Key":"CLUB_GPS_CLUBHOUSE_LATITUD","Value":"57.2111870"},{"Key":"CLUB_GPS_CLUBHOUSE_LONGITUD","Value":"13.7745744"},{"Key":"CLUB_GREENFEE_WEEKEND_JUNIOR","Value":"100"},{"Key":"CLUB_GREENFEE_WEEKEND_SENIOR","Value":"250"},{"Key":"CLUB_GREENFEE_WEEKDAY_JUNIOR","Value":"100"},{"Key":"CLUB_GREENFEE_WEEKDAY_SENIOR","Value":"250"},{"Key":"CLUB_GREENCARDCLUB","Value":"0"},{"Key":"CLUB_HCPFRIENDLY","Value":"1"},{"Key":"CLUB_HOMEPAGE","Value":"http://www.lannagk.se"},{"Key":"CLUB_DOGS_PROHIBITION","Value":"0"},{"Key":"CLUB_SHORTNAME","Value":"LanGK"},{"Key":"CLUB_CLUB_HIRE","Value":"1"},{"Key":"CLUB_SHORTTRACK","Value":"1"},{"Key":"CLUB_MOREGOLFKLUBB","Value":"0"},{"Key":"CLUB_LOCKERROOM","Value":"1"},{"Key":"CLUB_PAY_AND_PLAY","Value":"1"},{"Key":"CLUB_RESTAURANT","Value":"0"},{"Key":"CLUB_RESTRICTIONS","Value":"Bollränna\nÄngavattnet spelas med 9 greener och 18 tees.\nDagsgreenfee.\nTrantorpsbanan Pay & Play 9 korthål\n"},{"Key":"CLUB_SGF_NUMBER","Value":"372"},{"Key":"CLUB_SHOP","Value":"0"},{"Key":"CLUB_SPIKES","Value":"0"},{"Key":"CLUB_CABIN_HIRE","Value":"0"},{"Key":"CLUB_TRAILERPARK","Value":"1"},{"Key":"CLUB_TROLLEY_HIRE","Value":"1"},{"Key":"CLUB_PRACTICEGREEN","Value":"1"},{"Key":"CLUB_PRACTICEAREA","Value":"1"}],"ContactAvailabilities":[],"Contacts":[{"Type":"Ordförande","FirstName":"Sven","LastName":"Svensson","EmailAddress":null,"FullName":"Sven Svensson"}],"OtherClubs":null,"Emails":[{"EmailAddress":"Lannagolfklubb@gmail.com"}],"Tournaments":null,"Booking":null},"WeatherData":null}