{"GUID":"b59f2605-7e54-4875-bf98-ba618286a197","CountryISOCode":"SE","RegionGUID":"b9984d7d-2dc1-40e7-9f3b-dc5b63108a73","ID":"336","Name":"HaningeStrand Golfklubb","DisplayName":"HaningeStrand Golfklubb","ShortName":"HSGK","MapLat":"59.100662","MapLng":"18.196914","MapZoom":12,"ExternalID":"b59f2605-7e54-4875-bf98-ba618286a197","Data":{"Note":"Teknisk skogs- och parkbana i lätt kuperad natur.","WebPayment":"Ja","Courses":[{"Name":"Championship Course","Note":"18 hål teknisk skogs- och parkbana i lätt kuperad och vacker natur.","GeneralStartInfo":"","Loop":{"Name":"Championship course","Note":"Teknisk skogs och parkbana i lätt kuperad och vacker natur.","GreenNote":"Små och ganska ondulerade greener.","GreenOpen":true,"LoopOpen":true,"TemporaryGreens":false,"Active":true,"HCPAltering":true,"Slopes":[{"CourseRating":72.0,"SlopeValue":113,"Gender":0,"TeeColor":"I"},{"CourseRating":72.5,"SlopeValue":129,"Gender":1,"TeeColor":"I"},{"CourseRating":76.5,"SlopeValue":134,"Gender":0,"TeeColor":"II"},{"CourseRating":70.9,"SlopeValue":125,"Gender":1,"TeeColor":"II"},{"CourseRating":73.5,"SlopeValue":128,"Gender":0,"TeeColor":"III"},{"CourseRating":68.4,"SlopeValue":121,"Gender":1,"TeeColor":"III"},{"CourseRating":70.3,"SlopeValue":121,"Gender":0,"TeeColor":"IV"},{"CourseRating":65.8,"SlopeValue":115,"Gender":1,"TeeColor":"IV"},{"CourseRating":68.9,"SlopeValue":118,"Gender":0,"TeeColor":"V"},{"CourseRating":72.0,"SlopeValue":113,"Gender":1,"TeeColor":"V"}],"Holes":[{"Number":1,"Name":"Hål 01","Note":"","HoleSponsor":"","GreenCenterLatitude":null,"GreenCenterLongitude":null,"GreenFrontLatitude":null,"GreenFrontLongitude":null,"GrenDepth":0.0,"Tees":[{"Color":"V","ColorCode":null,"Length":210,"Type":"Grästee","TeeLatitude":null,"TeeLongitude":null},{"Color":"III","ColorCode":null,"Length":320,"Type":"Grästee","TeeLatitude":null,"TeeLongitude":null},{"Color":"IV","ColorCode":null,"Length":260,"Type":"Grästee","TeeLatitude":null,"TeeLongitude":null},{"Color":"I","ColorCode":null,"Length":360,"Type":"Grästee","TeeLatitude":null,"TeeLongitude":null},{"Color":"II","ColorCode":null,"Length":320,"Type":"Grästee","TeeLatitude":null,"TeeLongitude":null}],"Par":4,"Index":5},{"Number":2,"Name":"Hål 02","Note":"","HoleSponsor":"","GreenCenterLatitude":null,"GreenCenterLongitude":null,"GreenFrontLatitude":null,"GreenFrontLongitude":null,"GrenDepth":0.0,"Tees":[{"Color":"V","ColorCode":null,"Length":315,"Type":"Grästee","TeeLatitude":null,"TeeLongitude":null},{"Color":"III","ColorCode":null,"Length":355,"Type":"Grästee","TeeLatitude":null,"TeeLongitude":null},{"Color":"IV","ColorCode":null,"Length":355,"Type":"Grästee","TeeLatitude":null,"TeeLongitude":null},{"Color":"I","ColorCode":null,"Length":495,"Type":"Grästee","TeeLatitude":null,"TeeLongitude":null},{"Color":"II","ColorCode":null,"Length":455,"Type":"Grästee","TeeLatitude":null,"TeeLongitude":null}],"Par":5,"Index":7},{"Number":3,"Name":"Hål 03","Note":"","HoleSponsor":"","GreenCenterLatitude":null,"GreenCenterLongitude":null,"GreenFrontLatitude":null,"GreenFrontLongitude":null,"GrenDepth":0.0,"Tees":[{"Color":"V","ColorCode":null,"Length":365,"Type":"Grästee","TeeLatitude":null,"TeeLongitude":null},{"Color":"III","ColorCode":null,"Length":425,"Type":"Grästee","TeeLatitude":null,"TeeLongitude":null},{"Color":"IV","ColorCode":null,"Length":365,"Type":"Grästee","TeeLatitude":null,"TeeLongitude":null},{"Color":"I","ColorCode":null,"Length":480,"Type":"Grästee","TeeLatitude":null,"TeeLongitude":null},{"Color":"II","ColorCode":null,"Length":475,"Type":"Grästee","TeeLatitude":null,"TeeLongitude":null}],"Par":5,"Index":3},{"Number":4,"Name":"Hål 04","Note":"","HoleSponsor":"","GreenCenterLatitude":null,"GreenCenterLongitude":null,"GreenFrontLatitude":null,"GreenFrontLongitude":null,"GrenDepth":0.0,"Tees":[{"Color":"V","ColorCode":null,"Length":245,"Type":"Grästee","TeeLatitude":null,"TeeLongitude":null},{"Color":"III","ColorCode":null,"Length":310,"Type":"Grästee","TeeLatitude":null,"TeeLongitude":null},{"Color":"IV","ColorCode":null,"Length":310,"Type":"Grästee","TeeLatitude":null,"TeeLongitude":null},{"Color":"I","ColorCode":null,"Length":390,"Type":"Grästee","TeeLatitude":null,"TeeLongitude":null},{"Color":"II","ColorCode":null,"Length":375,"Type":"Grästee","TeeLatitude":null,"TeeLongitude":null}],"Par":4,"Index":9},{"Number":5,"Name":"Hål 05","Note":"","HoleSponsor":"","GreenCenterLatitude":null,"GreenCenterLongitude":null,"GreenFrontLatitude":null,"GreenFrontLongitude":null,"GrenDepth":0.0,"Tees":[{"Color":"V","ColorCode":null,"Length":240,"Type":"Grästee","TeeLatitude":null,"TeeLongitude":null},{"Color":"III","ColorCode":null,"Length":280,"Type":"Grästee","TeeLatitude":null,"TeeLongitude":null},{"Color":"IV","ColorCode":null,"Length":240,"Type":"Grästee","TeeLatitude":null,"TeeLongitude":null},{"Color":"I","ColorCode":null,"Length":300,"Type":"Grästee","TeeLatitude":null,"TeeLongitude":null},{"Color":"II","ColorCode":null,"Length":280,"Type":"Grästee","TeeLatitude":null,"TeeLongitude":null}],"Par":4,"Index":11},{"Number":6,"Name":"Hål 06","Note":"","HoleSponsor":"","GreenCenterLatitude":null,"GreenCenterLongitude":null,"GreenFrontLatitude":null,"GreenFrontLongitude":null,"GrenDepth":0.0,"Tees":[{"Color":"V","ColorCode":null,"Length":125,"Type":"Grästee","TeeLatitude":null,"TeeLongitude":null},{"Color":"III","ColorCode":null,"Length":145,"Type":"Grästee","TeeLatitude":null,"TeeLongitude":null},{"Color":"IV","ColorCode":null,"Length":125,"Type":"Grästee","TeeLatitude":null,"TeeLongitude":null},{"Color":"I","ColorCode":null,"Length":165,"Type":"Grästee","TeeLatitude":null,"TeeLongitude":null},{"Color":"II","ColorCode":null,"Length":145,"Type":"Grästee","TeeLatitude":null,"TeeLongitude":null}],"Par":3,"Index":17},{"Number":7,"Name":"Hål 07","Note":"","HoleSponsor":"","GreenCenterLatitude":null,"GreenCenterLongitude":null,"GreenFrontLatitude":null,"GreenFrontLongitude":null,"GrenDepth":0.0,"Tees":[{"Color":"V","ColorCode":null,"Length":240,"Type":"Grästee","TeeLatitude":null,"TeeLongitude":null},{"Color":"III","ColorCode":null,"Length":310,"Type":"Grästee","TeeLatitude":null,"TeeLongitude":null},{"Color":"IV","ColorCode":null,"Length":240,"Type":"Grästee","TeeLatitude":null,"TeeLongitude":null},{"Color":"I","ColorCode":null,"Length":385,"Type":"Grästee","TeeLatitude":null,"TeeLongitude":null},{"Color":"II","ColorCode":null,"Length":375,"Type":"Grästee","TeeLatitude":null,"TeeLongitude":null}],"Par":4,"Index":1},{"Number":8,"Name":"Hål 08","Note":"","HoleSponsor":"","GreenCenterLatitude":null,"GreenCenterLongitude":null,"GreenFrontLatitude":null,"GreenFrontLongitude":null,"GrenDepth":0.0,"Tees":[{"Color":"V","ColorCode":null,"Length":130,"Type":"Grästee","TeeLatitude":null,"TeeLongitude":null},{"Color":"III","ColorCode":null,"Length":150,"Type":"Grästee","TeeLatitude":null,"TeeLongitude":null},{"Color":"IV","ColorCode":null,"Length":130,"Type":"Grästee","TeeLatitude":null,"TeeLongitude":null},{"Color":"I","ColorCode":null,"Length":170,"Type":"Grästee","TeeLatitude":null,"TeeLongitude":null},{"Color":"II","ColorCode":null,"Length":150,"Type":"Grästee","TeeLatitude":null,"TeeLongitude":null}],"Par":3,"Index":13},{"Number":9,"Name":"Hål 09","Note":"","HoleSponsor":"","GreenCenterLatitude":null,"GreenCenterLongitude":null,"GreenFrontLatitude":null,"GreenFrontLongitude":null,"GrenDepth":0.0,"Tees":[{"Color":"V","ColorCode":null,"Length":240,"Type":"Grästee","TeeLatitude":null,"TeeLongitude":null},{"Color":"III","ColorCode":null,"Length":280,"Type":"Grästee","TeeLatitude":null,"TeeLongitude":null},{"Color":"IV","ColorCode":null,"Length":240,"Type":"Grästee","TeeLatitude":null,"TeeLongitude":null},{"Color":"I","ColorCode":null,"Length":310,"Type":"Grästee","TeeLatitude":null,"TeeLongitude":null},{"Color":"II","ColorCode":null,"Length":280,"Type":"Grästee","TeeLatitude":null,"TeeLongitude":null}],"Par":4,"Index":15},{"Number":10,"Name":"Hål 10","Note":"","HoleSponsor":"","GreenCenterLatitude":null,"GreenCenterLongitude":null,"GreenFrontLatitude":null,"GreenFrontLongitude":null,"GrenDepth":0.0,"Tees":[{"Color":"V","ColorCode":null,"Length":245,"Type":"Grästee","TeeLatitude":null,"TeeLongitude":null},{"Color":"III","ColorCode":null,"Length":310,"Type":"Grästee","TeeLatitude":null,"TeeLongitude":null},{"Color":"IV","ColorCode":null,"Length":245,"Type":"Grästee","TeeLatitude":null,"TeeLongitude":null},{"Color":"I","ColorCode":null,"Length":320,"Type":"Grästee","TeeLatitude":null,"TeeLongitude":null},{"Color":"II","ColorCode":null,"Length":310,"Type":"Grästee","TeeLatitude":null,"TeeLongitude":null}],"Par":4,"Index":6},{"Number":11,"Name":"Hål 11","Note":"","HoleSponsor":"","GreenCenterLatitude":null,"GreenCenterLongitude":null,"GreenFrontLatitude":null,"GreenFrontLongitude":null,"GrenDepth":0.0,"Tees":[{"Color":"V","ColorCode":null,"Length":85,"Type":"Grästee","TeeLatitude":null,"TeeLongitude":null},{"Color":"III","ColorCode":null,"Length":110,"Type":"Grästee","TeeLatitude":null,"TeeLongitude":null},{"Color":"IV","ColorCode":null,"Length":85,"Type":"Grästee","TeeLatitude":null,"TeeLongitude":null},{"Color":"I","ColorCode":null,"Length":135,"Type":"Grästee","TeeLatitude":null,"TeeLongitude":null},{"Color":"II","ColorCode":null,"Length":125,"Type":"Grästee","TeeLatitude":null,"TeeLongitude":null}],"Par":3,"Index":10},{"Number":12,"Name":"Hål 12","Note":"","HoleSponsor":"","GreenCenterLatitude":null,"GreenCenterLongitude":null,"GreenFrontLatitude":null,"GreenFrontLongitude":null,"GrenDepth":0.0,"Tees":[{"Color":"V","ColorCode":null,"Length":335,"Type":"Grästee","TeeLatitude":null,"TeeLongitude":null},{"Color":"III","ColorCode":null,"Length":355,"Type":"Grästee","TeeLatitude":null,"TeeLongitude":null},{"Color":"IV","ColorCode":null,"Length":335,"Type":"Grästee","TeeLatitude":null,"TeeLongitude":null},{"Color":"I","ColorCode":null,"Length":460,"Type":"Grästee","TeeLatitude":null,"TeeLongitude":null},{"Color":"II","ColorCode":null,"Length":440,"Type":"Grästee","TeeLatitude":null,"TeeLongitude":null}],"Par":5,"Index":14},{"Number":13,"Name":"Hål 13","Note":"","HoleSponsor":"","GreenCenterLatitude":null,"GreenCenterLongitude":null,"GreenFrontLatitude":null,"GreenFrontLongitude":null,"GrenDepth":0.0,"Tees":[{"Color":"V","ColorCode":null,"Length":255,"Type":"Grästee","TeeLatitude":null,"TeeLongitude":null},{"Color":"III","ColorCode":null,"Length":305,"Type":"Grästee","TeeLatitude":null,"TeeLongitude":null},{"Color":"IV","ColorCode":null,"Length":285,"Type":"Grästee","TeeLatitude":null,"TeeLongitude":null},{"Color":"I","ColorCode":null,"Length":340,"Type":"Grästee","TeeLatitude":null,"TeeLongitude":null},{"Color":"II","ColorCode":null,"Length":305,"Type":"Grästee","TeeLatitude":null,"TeeLongitude":null}],"Par":4,"Index":18},{"Number":14,"Name":"Hål 14","Note":"","HoleSponsor":"","GreenCenterLatitude":null,"GreenCenterLongitude":null,"GreenFrontLatitude":null,"GreenFrontLongitude":null,"GrenDepth":0.0,"Tees":[{"Color":"V","ColorCode":null,"Length":120,"Type":"Grästee","TeeLatitude":null,"TeeLongitude":null},{"Color":"III","ColorCode":null,"Length":120,"Type":"Grästee","TeeLatitude":null,"TeeLongitude":null},{"Color":"IV","ColorCode":null,"Length":120,"Type":"Grästee","TeeLatitude":null,"TeeLongitude":null},{"Color":"I","ColorCode":null,"Length":170,"Type":"Grästee","TeeLatitude":null,"TeeLongitude":null},{"Color":"II","ColorCode":null,"Length":145,"Type":"Grästee","TeeLatitude":null,"TeeLongitude":null}],"Par":3,"Index":16},{"Number":15,"Name":"Hål 15","Note":"","HoleSponsor":"","GreenCenterLatitude":null,"GreenCenterLongitude":null,"GreenFrontLatitude":null,"GreenFrontLongitude":null,"GrenDepth":0.0,"Tees":[{"Color":"V","ColorCode":null,"Length":390,"Type":"Grästee","TeeLatitude":null,"TeeLongitude":null},{"Color":"III","ColorCode":null,"Length":390,"Type":"Grästee","TeeLatitude":null,"TeeLongitude":null},{"Color":"IV","ColorCode":null,"Length":390,"Type":"Grästee","TeeLatitude":null,"TeeLongitude":null},{"Color":"I","ColorCode":null,"Length":450,"Type":"Grästee","TeeLatitude":null,"TeeLongitude":null},{"Color":"II","ColorCode":null,"Length":440,"Type":"Grästee","TeeLatitude":null,"TeeLongitude":null}],"Par":5,"Index":12},{"Number":16,"Name":"Hål 16","Note":"","HoleSponsor":"","GreenCenterLatitude":null,"GreenCenterLongitude":null,"GreenFrontLatitude":null,"GreenFrontLongitude":null,"GrenDepth":0.0,"Tees":[{"Color":"V","ColorCode":null,"Length":275,"Type":"Grästee","TeeLatitude":null,"TeeLongitude":null},{"Color":"III","ColorCode":null,"Length":335,"Type":"Grästee","TeeLatitude":null,"TeeLongitude":null},{"Color":"IV","ColorCode":null,"Length":275,"Type":"Grästee","TeeLatitude":null,"TeeLongitude":null},{"Color":"I","ColorCode":null,"Length":345,"Type":"Grästee","TeeLatitude":null,"TeeLongitude":null},{"Color":"II","ColorCode":null,"Length":335,"Type":"Grästee","TeeLatitude":null,"TeeLongitude":null}],"Par":4,"Index":4},{"Number":17,"Name":"Hål 17","Note":"","HoleSponsor":"","GreenCenterLatitude":null,"GreenCenterLongitude":null,"GreenFrontLatitude":null,"GreenFrontLongitude":null,"GrenDepth":0.0,"Tees":[{"Color":"V","ColorCode":null,"Length":100,"Type":"Grästee","TeeLatitude":null,"TeeLongitude":null},{"Color":"III","ColorCode":null,"Length":150,"Type":"Grästee","TeeLatitude":null,"TeeLongitude":null},{"Color":"IV","ColorCode":null,"Length":115,"Type":"Grästee","TeeLatitude":null,"TeeLongitude":null},{"Color":"I","ColorCode":null,"Length":160,"Type":"Grästee","TeeLatitude":null,"TeeLongitude":null},{"Color":"II","ColorCode":null,"Length":150,"Type":"Grästee","TeeLatitude":null,"TeeLongitude":null}],"Par":3,"Index":8},{"Number":18,"Name":"Hål 18","Note":"","HoleSponsor":"","GreenCenterLatitude":null,"GreenCenterLongitude":null,"GreenFrontLatitude":null,"GreenFrontLongitude":null,"GrenDepth":0.0,"Tees":[{"Color":"V","ColorCode":null,"Length":380,"Type":"Grästee","TeeLatitude":null,"TeeLongitude":null},{"Color":"III","ColorCode":null,"Length":425,"Type":"Grästee","TeeLatitude":null,"TeeLongitude":null},{"Color":"IV","ColorCode":null,"Length":425,"Type":"Grästee","TeeLatitude":null,"TeeLongitude":null},{"Color":"I","ColorCode":null,"Length":565,"Type":"Grästee","TeeLatitude":null,"TeeLongitude":null},{"Color":"II","ColorCode":null,"Length":510,"Type":"Grästee","TeeLatitude":null,"TeeLongitude":null}],"Par":5,"Index":2}],"ValidFrom":"20200122T000000","ValidTo":"20201130T000000","GPSInfoOK":false},"BookingInformation":"Banan är öppen. Restaurang/Kiosk: öppet alla dagar 8-20, lunch serveras 11-15. Reception/Shop: öppet alla dagar 8-16. Förbjudet att beträda banan vid frost. Vid frågor ring 08-707 06 60. ","NumberOfHoles":18,"Par":72,"Architect":"Bengt Lorichs","PlayableFromYear":""}],"Phones":[{"Number":"+4687070660","PhoneType":"Primary"},{"Number":"+4687070660","PhoneType":"Bokning"},{"Number":"+4687070660","PhoneType":"Kansli"}],"Addresses":[{"Addr":"Lindersbergsvägen 21","AddrInfo1":"","AddrInfo2":null,"PostalCode":"13795","PostalAddress":"ÖSTERHANINGE","Region":null,"Country":null,"Type":null}],"ClubAttributes":[{"Key":"CLUB_RESIDENT","Value":"1"},{"Key":"CLUB_CAFE","Value":"1"},{"Key":"CLUB_DRIVINGRANGE","Value":"1"},{"Key":"CLUB_SHOWER","Value":"1"},{"Key":"CLUB_TRAILERPARK_ELECTRIC_SOCKETS","Value":"1"},{"Key":"CLUB_BUGGY_HIRE","Value":"1"},{"Key":"GOLF_PACKAGES","Value":"0"},{"Key":"PROSHOP_EMAIL","Value":"rikard.naslund@pgasweden.com"},{"Key":"PROSHOP_CONTACT","Value":"Rikard Näslund"},{"Key":"PROSHOP_NAME","Value":"HaningeStrand Golfshop"},{"Key":"PROSHOP_PHONE","Value":"+46708584058"},{"Key":"PROSHOP_HOMEPAGE_URL","Value":"www.haningestrand.se"},{"Key":"RESTAURANT_EMAIL","Value":"hakan.larsson@haningestrand.se"},{"Key":"RESTAURANT_CONTACT","Value":"Håkan Larsson"},{"Key":"RESTAURANT_NAME","Value":"HaningeStrand Nitton"},{"Key":"RESTAURANT_PHONE","Value":"+4687070660"},{"Key":"RESTAURANT_HOMEPAGE_URL","Value":"www.haningestrand.se"},{"Key":"CLUB_GPS_CLUBHOUSE_LATITUD","Value":"59.100662"},{"Key":"CLUB_GPS_CLUBHOUSE_LONGITUD","Value":"18.196914"},{"Key":"CLUB_GREENFEE_WEEKEND_JUNIOR","Value":""},{"Key":"CLUB_GREENFEE_WEEKEND_SENIOR","Value":""},{"Key":"CLUB_GREENFEE_TEXT","Value":"Differentierad"},{"Key":"CLUB_GREENFEE_WEEKDAY_JUNIOR","Value":""},{"Key":"CLUB_GREENFEE_WEEKDAY_SENIOR","Value":""},{"Key":"CLUB_GREENCARDCLUB","Value":"1"},{"Key":"CLUB_HCPFRIENDLY","Value":"1"},{"Key":"CLUB_HOMEPAGE","Value":"www.haningestrand.se"},{"Key":"CLUB_DOGS_PROHIBITION","Value":"0"},{"Key":"CLUB_SHORTNAME","Value":"HSGK"},{"Key":"CLUB_CLUB_HIRE","Value":"1"},{"Key":"CLUB_SHORTTRACK","Value":"0"},{"Key":"CLUB_MOREGOLFKLUBB","Value":"0"},{"Key":"CLUB_LOCKERROOM","Value":"1"},{"Key":"CLUB_PAY_AND_PLAY","Value":"0"},{"Key":"CLUB_RESTAURANT","Value":"1"},{"Key":"CLUB_RESTRICTIONS","Value":""},{"Key":"CLUB_SGF_NUMBER","Value":"336"},{"Key":"CLUB_SHOP","Value":"1"},{"Key":"CLUB_SPIKES","Value":"1"},{"Key":"CLUB_CABIN_HIRE","Value":"0"},{"Key":"CLUB_TRAILERPARK","Value":"1"},{"Key":"CLUB_TROLLEY_HIRE","Value":"1"},{"Key":"CLUB_PRACTICEGREEN","Value":"1"},{"Key":"CLUB_PRACTICEAREA","Value":"1"}],"ContactAvailabilities":[],"Contacts":[{"Type":"Klubbchef/VD/Intendent","FirstName":"Paul","LastName":"Youngman","EmailAddress":null,"FullName":"Paul Youngman"},{"Type":"Ordförande","FirstName":"Kjell","LastName":"Eriksson","EmailAddress":null,"FullName":"Kjell Eriksson"}],"OtherClubs":null,"Emails":[{"EmailAddress":"info@haningestrand.se"}],"Tournaments":null,"Booking":null},"WeatherData":null}