{"GUID":"ebe00954-3982-46e2-9d2a-eeba5c03f7ec","CountryISOCode":"SE","RegionGUID":"0023d53d-b3ce-458b-a88b-5baf111ec7cd","ID":"254","Name":"Skogaby Golfklubb","DisplayName":"Skogaby Golfklubb","ShortName":"SbyGK","MapLat":"56.540072126537396","MapLng":"13.173284149169922","MapZoom":12,"ExternalID":"ebe00954-3982-46e2-9d2a-eeba5c03f7ec","Data":{"Note":"Klubb","WebPayment":"Ja","Courses":[{"Name":"Skogaby","Note":"Hål nr 1-18","GeneralStartInfo":"","Loop":{"Name":"Skogaby Golfbana","Note":"Hål nr 1-18","GreenNote":"","GreenOpen":true,"LoopOpen":true,"TemporaryGreens":true,"Active":true,"HCPAltering":true,"Slopes":[{"CourseRating":76.7,"SlopeValue":135,"Gender":0,"TeeColor":"Vit"},{"CourseRating":70.2,"SlopeValue":126,"Gender":1,"TeeColor":"Vit"},{"CourseRating":74.8,"SlopeValue":128,"Gender":0,"TeeColor":"Gul"},{"CourseRating":69.2,"SlopeValue":124,"Gender":1,"TeeColor":"Gul"},{"CourseRating":72.8,"SlopeValue":124,"Gender":0,"TeeColor":"Blå"},{"CourseRating":67.6,"SlopeValue":121,"Gender":1,"TeeColor":"Blå"},{"CourseRating":70.5,"SlopeValue":119,"Gender":0,"TeeColor":"Röd"},{"CourseRating":65.7,"SlopeValue":117,"Gender":1,"TeeColor":"Röd"},{"CourseRating":66.6,"SlopeValue":111,"Gender":0,"TeeColor":"Orange"},{"CourseRating":64.1,"SlopeValue":117,"Gender":1,"TeeColor":"Orange"}],"Holes":[{"Number":1,"Name":"Hål nr 1","Note":"","HoleSponsor":"","GreenCenterLatitude":null,"GreenCenterLongitude":null,"GreenFrontLatitude":null,"GreenFrontLongitude":null,"GrenDepth":0.0,"Tees":[{"Color":"Orange","ColorCode":null,"Length":216,"Type":"Grästee","TeeLatitude":null,"TeeLongitude":null},{"Color":"Blå","ColorCode":null,"Length":287,"Type":"Grästee","TeeLatitude":null,"TeeLongitude":null},{"Color":"Röd","ColorCode":null,"Length":280,"Type":"Grästee","TeeLatitude":null,"TeeLongitude":null},{"Color":"Vit","ColorCode":null,"Length":330,"Type":"Grästee","TeeLatitude":null,"TeeLongitude":null},{"Color":"Gul","ColorCode":null,"Length":320,"Type":"Grästee","TeeLatitude":null,"TeeLongitude":null}],"Par":4,"Index":10},{"Number":2,"Name":"Hål nr 2","Note":"","HoleSponsor":"","GreenCenterLatitude":null,"GreenCenterLongitude":null,"GreenFrontLatitude":null,"GreenFrontLongitude":null,"GrenDepth":0.0,"Tees":[{"Color":"Orange","ColorCode":null,"Length":140,"Type":"Grästee","TeeLatitude":null,"TeeLongitude":null},{"Color":"Blå","ColorCode":null,"Length":145,"Type":"Grästee","TeeLatitude":null,"TeeLongitude":null},{"Color":"Röd","ColorCode":null,"Length":140,"Type":"Grästee","TeeLatitude":null,"TeeLongitude":null},{"Color":"Vit","ColorCode":null,"Length":161,"Type":"Grästee","TeeLatitude":null,"TeeLongitude":null},{"Color":"Gul","ColorCode":null,"Length":155,"Type":"Grästee","TeeLatitude":null,"TeeLongitude":null}],"Par":3,"Index":12},{"Number":3,"Name":"Hål nr 3","Note":"","HoleSponsor":"","GreenCenterLatitude":null,"GreenCenterLongitude":null,"GreenFrontLatitude":null,"GreenFrontLongitude":null,"GrenDepth":0.0,"Tees":[{"Color":"Orange","ColorCode":null,"Length":236,"Type":"Grästee","TeeLatitude":null,"TeeLongitude":null},{"Color":"Blå","ColorCode":null,"Length":365,"Type":"Grästee","TeeLatitude":null,"TeeLongitude":null},{"Color":"Röd","ColorCode":null,"Length":300,"Type":"Grästee","TeeLatitude":null,"TeeLongitude":null},{"Color":"Vit","ColorCode":null,"Length":397,"Type":"Grästee","TeeLatitude":null,"TeeLongitude":null},{"Color":"Gul","ColorCode":null,"Length":385,"Type":"Grästee","TeeLatitude":null,"TeeLongitude":null}],"Par":4,"Index":2},{"Number":4,"Name":"Hål nr 4","Note":"","HoleSponsor":"","GreenCenterLatitude":null,"GreenCenterLongitude":null,"GreenFrontLatitude":null,"GreenFrontLongitude":null,"GrenDepth":0.0,"Tees":[{"Color":"Orange","ColorCode":null,"Length":335,"Type":"Grästee","TeeLatitude":null,"TeeLongitude":null},{"Color":"Blå","ColorCode":null,"Length":417,"Type":"Grästee","TeeLatitude":null,"TeeLongitude":null},{"Color":"Röd","ColorCode":null,"Length":415,"Type":"Grästee","TeeLatitude":null,"TeeLongitude":null},{"Color":"Vit","ColorCode":null,"Length":485,"Type":"Grästee","TeeLatitude":null,"TeeLongitude":null},{"Color":"Gul","ColorCode":null,"Length":460,"Type":"Grästee","TeeLatitude":null,"TeeLongitude":null}],"Par":5,"Index":8},{"Number":5,"Name":"Hål nr 5","Note":"","HoleSponsor":"","GreenCenterLatitude":null,"GreenCenterLongitude":null,"GreenFrontLatitude":null,"GreenFrontLongitude":null,"GrenDepth":0.0,"Tees":[{"Color":"Orange","ColorCode":null,"Length":240,"Type":"Grästee","TeeLatitude":null,"TeeLongitude":null},{"Color":"Blå","ColorCode":null,"Length":272,"Type":"Grästee","TeeLatitude":null,"TeeLongitude":null},{"Color":"Röd","ColorCode":null,"Length":240,"Type":"Grästee","TeeLatitude":null,"TeeLongitude":null},{"Color":"Vit","ColorCode":null,"Length":296,"Type":"Grästee","TeeLatitude":null,"TeeLongitude":null},{"Color":"Gul","ColorCode":null,"Length":280,"Type":"Grästee","TeeLatitude":null,"TeeLongitude":null}],"Par":4,"Index":6},{"Number":6,"Name":"Hål nr 6","Note":"","HoleSponsor":"","GreenCenterLatitude":null,"GreenCenterLongitude":null,"GreenFrontLatitude":null,"GreenFrontLongitude":null,"GrenDepth":0.0,"Tees":[{"Color":"Orange","ColorCode":null,"Length":105,"Type":"Grästee","TeeLatitude":null,"TeeLongitude":null},{"Color":"Blå","ColorCode":null,"Length":131,"Type":"Grästee","TeeLatitude":null,"TeeLongitude":null},{"Color":"Röd","ColorCode":null,"Length":105,"Type":"Grästee","TeeLatitude":null,"TeeLongitude":null},{"Color":"Vit","ColorCode":null,"Length":157,"Type":"Grästee","TeeLatitude":null,"TeeLongitude":null},{"Color":"Gul","ColorCode":null,"Length":135,"Type":"Grästee","TeeLatitude":null,"TeeLongitude":null}],"Par":3,"Index":18},{"Number":7,"Name":"Hål nr 7","Note":"","HoleSponsor":"","GreenCenterLatitude":null,"GreenCenterLongitude":null,"GreenFrontLatitude":null,"GreenFrontLongitude":null,"GrenDepth":0.0,"Tees":[{"Color":"Orange","ColorCode":null,"Length":225,"Type":"Grästee","TeeLatitude":null,"TeeLongitude":null},{"Color":"Blå","ColorCode":null,"Length":306,"Type":"Grästee","TeeLatitude":null,"TeeLongitude":null},{"Color":"Röd","ColorCode":null,"Length":260,"Type":"Grästee","TeeLatitude":null,"TeeLongitude":null},{"Color":"Vit","ColorCode":null,"Length":315,"Type":"Grästee","TeeLatitude":null,"TeeLongitude":null},{"Color":"Gul","ColorCode":null,"Length":310,"Type":"Grästee","TeeLatitude":null,"TeeLongitude":null}],"Par":4,"Index":4},{"Number":8,"Name":"Hål nr 8","Note":"","HoleSponsor":"","GreenCenterLatitude":null,"GreenCenterLongitude":null,"GreenFrontLatitude":null,"GreenFrontLongitude":null,"GrenDepth":0.0,"Tees":[{"Color":"Orange","ColorCode":null,"Length":330,"Type":"Grästee","TeeLatitude":null,"TeeLongitude":null},{"Color":"Blå","ColorCode":null,"Length":421,"Type":"Grästee","TeeLatitude":null,"TeeLongitude":null},{"Color":"Röd","ColorCode":null,"Length":410,"Type":"Grästee","TeeLatitude":null,"TeeLongitude":null},{"Color":"Vit","ColorCode":null,"Length":452,"Type":"Grästee","TeeLatitude":null,"TeeLongitude":null},{"Color":"Gul","ColorCode":null,"Length":445,"Type":"Grästee","TeeLatitude":null,"TeeLongitude":null}],"Par":5,"Index":16},{"Number":9,"Name":"Hål nr 9","Note":"","HoleSponsor":"","GreenCenterLatitude":null,"GreenCenterLongitude":null,"GreenFrontLatitude":null,"GreenFrontLongitude":null,"GrenDepth":0.0,"Tees":[{"Color":"Orange","ColorCode":null,"Length":270,"Type":"Grästee","TeeLatitude":null,"TeeLongitude":null},{"Color":"Blå","ColorCode":null,"Length":275,"Type":"Grästee","TeeLatitude":null,"TeeLongitude":null},{"Color":"Röd","ColorCode":null,"Length":270,"Type":"Grästee","TeeLatitude":null,"TeeLongitude":null},{"Color":"Vit","ColorCode":null,"Length":336,"Type":"Grästee","TeeLatitude":null,"TeeLongitude":null},{"Color":"Gul","ColorCode":null,"Length":315,"Type":"Grästee","TeeLatitude":null,"TeeLongitude":null}],"Par":4,"Index":14},{"Number":10,"Name":"Hål nr 10","Note":"","HoleSponsor":"","GreenCenterLatitude":null,"GreenCenterLongitude":null,"GreenFrontLatitude":null,"GreenFrontLongitude":null,"GrenDepth":0.0,"Tees":[{"Color":"Orange","ColorCode":null,"Length":261,"Type":"Grästee","TeeLatitude":null,"TeeLongitude":null},{"Color":"Blå","ColorCode":null,"Length":327,"Type":"Grästee","TeeLatitude":null,"TeeLongitude":null},{"Color":"Röd","ColorCode":null,"Length":320,"Type":"Grästee","TeeLatitude":null,"TeeLongitude":null},{"Color":"Vit","ColorCode":null,"Length":393,"Type":"Grästee","TeeLatitude":null,"TeeLongitude":null},{"Color":"Gul","ColorCode":null,"Length":365,"Type":"Grästee","TeeLatitude":null,"TeeLongitude":null}],"Par":4,"Index":11},{"Number":11,"Name":"Hål nr 11","Note":"","HoleSponsor":"","GreenCenterLatitude":null,"GreenCenterLongitude":null,"GreenFrontLatitude":null,"GreenFrontLongitude":null,"GrenDepth":0.0,"Tees":[{"Color":"Orange","ColorCode":null,"Length":313,"Type":"Grästee","TeeLatitude":null,"TeeLongitude":null},{"Color":"Blå","ColorCode":null,"Length":417,"Type":"Grästee","TeeLatitude":null,"TeeLongitude":null},{"Color":"Röd","ColorCode":null,"Length":370,"Type":"Grästee","TeeLatitude":null,"TeeLongitude":null},{"Color":"Vit","ColorCode":null,"Length":457,"Type":"Grästee","TeeLatitude":null,"TeeLongitude":null},{"Color":"Gul","ColorCode":null,"Length":425,"Type":"Grästee","TeeLatitude":null,"TeeLongitude":null}],"Par":5,"Index":15},{"Number":12,"Name":"Hål nr 12","Note":"","HoleSponsor":"","GreenCenterLatitude":null,"GreenCenterLongitude":null,"GreenFrontLatitude":null,"GreenFrontLongitude":null,"GrenDepth":0.0,"Tees":[{"Color":"Orange","ColorCode":null,"Length":251,"Type":"Grästee","TeeLatitude":null,"TeeLongitude":null},{"Color":"Blå","ColorCode":null,"Length":345,"Type":"Grästee","TeeLatitude":null,"TeeLongitude":null},{"Color":"Röd","ColorCode":null,"Length":325,"Type":"Grästee","TeeLatitude":null,"TeeLongitude":null},{"Color":"Vit","ColorCode":null,"Length":385,"Type":"Grästee","TeeLatitude":null,"TeeLongitude":null},{"Color":"Gul","ColorCode":null,"Length":360,"Type":"Grästee","TeeLatitude":null,"TeeLongitude":null}],"Par":4,"Index":1},{"Number":13,"Name":"Hål nr 13","Note":"","HoleSponsor":"","GreenCenterLatitude":null,"GreenCenterLongitude":null,"GreenFrontLatitude":null,"GreenFrontLongitude":null,"GrenDepth":0.0,"Tees":[{"Color":"Orange","ColorCode":null,"Length":125,"Type":"Grästee","TeeLatitude":null,"TeeLongitude":null},{"Color":"Blå","ColorCode":null,"Length":165,"Type":"Grästee","TeeLatitude":null,"TeeLongitude":null},{"Color":"Röd","ColorCode":null,"Length":125,"Type":"Grästee","TeeLatitude":null,"TeeLongitude":null},{"Color":"Vit","ColorCode":null,"Length":177,"Type":"Grästee","TeeLatitude":null,"TeeLongitude":null},{"Color":"Gul","ColorCode":null,"Length":170,"Type":"Grästee","TeeLatitude":null,"TeeLongitude":null}],"Par":3,"Index":5},{"Number":14,"Name":"Hål nr 14","Note":"","HoleSponsor":"","GreenCenterLatitude":null,"GreenCenterLongitude":null,"GreenFrontLatitude":null,"GreenFrontLongitude":null,"GrenDepth":0.0,"Tees":[{"Color":"Orange","ColorCode":null,"Length":270,"Type":"Grästee","TeeLatitude":null,"TeeLongitude":null},{"Color":"Blå","ColorCode":null,"Length":304,"Type":"Grästee","TeeLatitude":null,"TeeLongitude":null},{"Color":"Röd","ColorCode":null,"Length":270,"Type":"Grästee","TeeLatitude":null,"TeeLongitude":null},{"Color":"Vit","ColorCode":null,"Length":315,"Type":"Grästee","TeeLatitude":null,"TeeLongitude":null},{"Color":"Gul","ColorCode":null,"Length":310,"Type":"Grästee","TeeLatitude":null,"TeeLongitude":null}],"Par":4,"Index":13},{"Number":15,"Name":"Hål nr 15","Note":"","HoleSponsor":"","GreenCenterLatitude":null,"GreenCenterLongitude":null,"GreenFrontLatitude":null,"GreenFrontLongitude":null,"GrenDepth":0.0,"Tees":[{"Color":"Orange","ColorCode":null,"Length":103,"Type":"Grästee","TeeLatitude":null,"TeeLongitude":null},{"Color":"Blå","ColorCode":null,"Length":172,"Type":"Grästee","TeeLatitude":null,"TeeLongitude":null},{"Color":"Röd","ColorCode":null,"Length":160,"Type":"Grästee","TeeLatitude":null,"TeeLongitude":null},{"Color":"Vit","ColorCode":null,"Length":194,"Type":"Grästee","TeeLatitude":null,"TeeLongitude":null},{"Color":"Gul","ColorCode":null,"Length":185,"Type":"Grästee","TeeLatitude":null,"TeeLongitude":null}],"Par":3,"Index":3},{"Number":16,"Name":"Hål nr 16","Note":"","HoleSponsor":"","GreenCenterLatitude":null,"GreenCenterLongitude":null,"GreenFrontLatitude":null,"GreenFrontLongitude":null,"GrenDepth":0.0,"Tees":[{"Color":"Orange","ColorCode":null,"Length":120,"Type":"Grästee","TeeLatitude":null,"TeeLongitude":null},{"Color":"Blå","ColorCode":null,"Length":125,"Type":"Grästee","TeeLatitude":null,"TeeLongitude":null},{"Color":"Röd","ColorCode":null,"Length":120,"Type":"Grästee","TeeLatitude":null,"TeeLongitude":null},{"Color":"Vit","ColorCode":null,"Length":142,"Type":"Grästee","TeeLatitude":null,"TeeLongitude":null},{"Color":"Gul","ColorCode":null,"Length":135,"Type":"Grästee","TeeLatitude":null,"TeeLongitude":null}],"Par":3,"Index":7},{"Number":17,"Name":"Hål nr 17","Note":"","HoleSponsor":"","GreenCenterLatitude":null,"GreenCenterLongitude":null,"GreenFrontLatitude":null,"GreenFrontLongitude":null,"GrenDepth":0.0,"Tees":[{"Color":"Orange","ColorCode":null,"Length":350,"Type":"Grästee","TeeLatitude":null,"TeeLongitude":null},{"Color":"Blå","ColorCode":null,"Length":428,"Type":"Grästee","TeeLatitude":null,"TeeLongitude":null},{"Color":"Röd","ColorCode":null,"Length":420,"Type":"Grästee","TeeLatitude":null,"TeeLongitude":null},{"Color":"Vit","ColorCode":null,"Length":524,"Type":"Grästee","TeeLatitude":null,"TeeLongitude":null},{"Color":"Gul","ColorCode":null,"Length":515,"Type":"Grästee","TeeLatitude":null,"TeeLongitude":null}],"Par":5,"Index":9},{"Number":18,"Name":"Hål nr 18","Note":"","HoleSponsor":"","GreenCenterLatitude":null,"GreenCenterLongitude":null,"GreenFrontLatitude":null,"GreenFrontLongitude":null,"GrenDepth":0.0,"Tees":[{"Color":"Orange","ColorCode":null,"Length":240,"Type":"Grästee","TeeLatitude":null,"TeeLongitude":null},{"Color":"Blå","ColorCode":null,"Length":270,"Type":"Grästee","TeeLatitude":null,"TeeLongitude":null},{"Color":"Röd","ColorCode":null,"Length":240,"Type":"Grästee","TeeLatitude":null,"TeeLongitude":null},{"Color":"Vit","ColorCode":null,"Length":292,"Type":"Grästee","TeeLatitude":null,"TeeLongitude":null},{"Color":"Gul","ColorCode":null,"Length":275,"Type":"Grästee","TeeLatitude":null,"TeeLongitude":null}],"Par":4,"Index":17}],"ValidFrom":"20051201T000000","ValidTo":"20201101T000000","GPSInfoOK":false},"BookingInformation":"Kansliet är öppet måndag-fredag 09.00-15.00, lördag, söndag, helgdag 09.00-13.00.\nBokning av golfbil skall ske i god tid innan speldag. Är kansliet stängt lägger vi ut nycklar på receptionsdisken.","NumberOfHoles":18,"Par":71,"Architect":"Jonny Rosengren","PlayableFromYear":""}],"Phones":[{"Number":"+4643060190","PhoneType":"Primary"},{"Number":"+4643060190","PhoneType":"Bokning"},{"Number":"+4643060190","PhoneType":"Kansli"}],"Addresses":[{"Addr":"Kårarp","AddrInfo1":"","AddrInfo2":null,"PostalCode":"31293","PostalAddress":"LAHOLM","Region":null,"Country":null,"Type":null}],"ClubAttributes":[{"Key":"CLUB_RESIDENT","Value":"1"},{"Key":"CLUB_CAFE","Value":"1"},{"Key":"CLUB_DRIVINGRANGE","Value":"1"},{"Key":"CLUB_SHOWER","Value":"1"},{"Key":"CLUB_TRAILERPARK_ELECTRIC_SOCKETS","Value":"1"},{"Key":"CLUB_BUGGY_HIRE","Value":"1"},{"Key":"GOLFGUIDE_EXTENDEDINFO","Value":"Boende 24 bäddar finns på banan, se paketpriser hemsida skogabygk.se.  Parkering för husbil, husvagn finns till billig dygnshyra, el ingår. Tidbokning gäller mellan 06.30 och 18.00 1 april -30 sept. Bokning kan göras obegränsad tid före speldag."},{"Key":"GOLF_PACKAGES","Value":"0"},{"Key":"PROSHOP_EMAIL","Value":""},{"Key":"PROSHOP_CONTACT","Value":"Richard Edvinsson"},{"Key":"PROSHOP_NAME","Value":"R. Edvinsson Sport AB"},{"Key":"PROSHOP_PHONE","Value":"+4643060190"},{"Key":"PROSHOP_OPENING_HOURS","Value":"1 april - 31 oktober"},{"Key":"RESTAURANT_EMAIL","Value":""},{"Key":"RESTAURANT_CONTACT","Value":""},{"Key":"RESTAURANT_NAME","Value":"Skogaby Golfkrog"},{"Key":"RESTAURANT_PHONE","Value":""},{"Key":"RESTAURANT_HOMEPAGE_URL","Value":""},{"Key":"RESTAURANT_OPENING_HOURS","Value":"1 april - 31 oktober"},{"Key":"GOLFGUIDE_ROUTE_DESCR","Value":"Halmstad:Vid Eurostop väg 15 mot Markaryd.Efter 21 km avfart Blåalt.Skyltat Skogaby Golfklubb.  Laholm: Mot C följ Lagan till kraftverket, vägvisare Skogaby-Markaryd. Efter 8 km korsa väg 15 och kör in i Skogaby.\nMarkaryd: Väg 15, 30 km  mot Halmstad."},{"Key":"CLUB_GPS_CLUBHOUSE_LATITUD","Value":"56.540072126537396"},{"Key":"CLUB_GPS_CLUBHOUSE_LONGITUD","Value":"13.173284149169922"},{"Key":"CLUB_GREENFEE_WEEKEND_JUNIOR","Value":"200"},{"Key":"CLUB_GREENFEE_WEEKEND_SENIOR","Value":"400"},{"Key":"CLUB_GREENFEE_WEEKDAY_JUNIOR","Value":"175"},{"Key":"CLUB_GREENFEE_WEEKDAY_SENIOR","Value":"350"},{"Key":"CLUB_GREENCARDCLUB","Value":"1"},{"Key":"CLUB_HCPFRIENDLY","Value":"1"},{"Key":"CLUB_HOMEPAGE","Value":"http://www.skogabygk.se"},{"Key":"CLUB_DOGS_PROHIBITION","Value":"0"},{"Key":"CLUB_SHORTNAME","Value":"SbyGK"},{"Key":"CLUB_CLUB_HIRE","Value":"1"},{"Key":"CLUB_SHORTTRACK","Value":"0"},{"Key":"CLUB_MOREGOLFKLUBB","Value":"0"},{"Key":"CLUB_LOCKERROOM","Value":"1"},{"Key":"CLUB_PAY_AND_PLAY","Value":"0"},{"Key":"CLUB_RESTAURANT","Value":"1"},{"Key":"CLUB_RESTRICTIONS","Value":"Boende 24 bäddar finns på banan, paketpriser se hemsida. Parkering för husbil, husvagn finns till billig dygnshyra, el ingår. Tidbokning gäller mellan 06.30 och 18.00. Bokning kan göras obegränsad tid före speldag."},{"Key":"CLUB_SGF_NUMBER","Value":"254"},{"Key":"CLUB_SHOP","Value":"1"},{"Key":"CLUB_SPIKES","Value":"1"},{"Key":"CLUB_CABIN_HIRE","Value":"1"},{"Key":"CLUB_TRAILERPARK","Value":"1"},{"Key":"CLUB_TROLLEY_HIRE","Value":"1"},{"Key":"CLUB_PRACTICEGREEN","Value":"1"},{"Key":"CLUB_PRACTICEAREA","Value":"1"}],"ContactAvailabilities":[],"Contacts":[{"Type":"Ordförande","FirstName":"Johnny","LastName":"Nilsson","EmailAddress":null,"FullName":"Johnny Nilsson"}],"OtherClubs":null,"Emails":[{"EmailAddress":"info@skogabygk.se"}],"Tournaments":null,"Booking":null},"WeatherData":null}